hacmec_demo/__init__.py
hacmec_demo/__main__.py
hacmec_demo/config.py
hacmec_demo/crypto.py
hacmec_demo/demo.py
hacmec_demo/dnsupdate.py
hacmec_demo/py.typed
hacmec_demo-0.0.4.dist-info/METADATA
hacmec_demo-0.0.4.dist-info/WHEEL
hacmec_demo-0.0.4.dist-info/entry_points.txt
hacmec_demo-0.0.4.dist-info/top_level.txt
hacmec_demo-0.0.4.dist-info/zip-safe
hacmec_demo-0.0.4.dist-info/RECORD
